vessel_analysis_3d/__init__.py
vessel_analysis_3d/processing_pipeline.py
vessel_analysis_3d/bin/__init__.py
vessel_analysis_3d/bin/run_analysis.py
vessel_analysis_3d/graph/__init__.py
vessel_analysis_3d/graph/core.py
vessel_analysis_3d/graph/filament.py
vessel_analysis_3d/graph/measurement.py
vessel_analysis_3d/graph/networkx_from_array.py
vessel_analysis_3d/graph/stats_reporting.py
vessel_analysis_3d/tests/__init__.py
vessel_analysis_3d/tests/test_dummy.py
vessel_analysis_3d-0.1.1.dist-info/licenses/LICENSE
vessel_analysis_3d-0.1.1.dist-info/METADATA
vessel_analysis_3d-0.1.1.dist-info/WHEEL
vessel_analysis_3d-0.1.1.dist-info/entry_points.txt
vessel_analysis_3d-0.1.1.dist-info/top_level.txt
vessel_analysis_3d-0.1.1.dist-info/RECORD
