Metadata-Version: 2.4
Name: vessel_analysis_3d
Version: 0.1.1
Summary: A Python package for analyzing 3D vascular structures from segmentations
Author-email: Jianxu Chen <jianxuchen.ai@gmail.com>
License: MIT License
Project-URL: Homepage, https://github.com/MMV-Lab/vessel_analysis_3d
Keywords: vessel analysis,morphology,topology
Classifier: Development Status :: 2 - Pre-Alpha
Classifier: Intended Audience :: Developers
Classifier: Natural Language :: English
Classifier: Programming Language :: Python :: 3.10
Classifier: Programming Language :: Python :: 3.11
Requires-Python: >=3.10
License-File: LICENSE
Requires-Dist: bioio==1.6.1
Requires-Dist: bioio-ome-tiff==1.1.0
Requires-Dist: bioio-ome-zarr==1.2.0
Requires-Dist: bioio-tifffile==1.1.0
Requires-Dist: bioio-lif==1.1.0
Requires-Dist: scipy>=1.9.1
Requires-Dist: scikit-image>=0.19.3
Requires-Dist: networkx>=2.8.6
Requires-Dist: matplotlib>=3.6.0
Requires-Dist: geomdl>=5.3.1
Requires-Dist: botocore==1.38.38
Requires-Dist: lxml_html_clean
Provides-Extra: setup
Requires-Dist: pytest-runner>=5.2; extra == "setup"
Provides-Extra: test
Requires-Dist: black>=19.10b0; extra == "test"
Requires-Dist: codecov>=2.1.4; extra == "test"
Requires-Dist: flake8>=3.8.3; extra == "test"
Requires-Dist: flake8-debugger>=3.2.1; extra == "test"
Requires-Dist: pytest>=5.4.3; extra == "test"
Requires-Dist: pytest-cov>=2.9.0; extra == "test"
Requires-Dist: pytest-raises>=0.11; extra == "test"
Provides-Extra: dev
Requires-Dist: pytest-runner>=5.2; extra == "dev"
Requires-Dist: black>=19.10b0; extra == "dev"
Requires-Dist: codecov>=2.1.4; extra == "dev"
Requires-Dist: flake8>=3.8.3; extra == "dev"
Requires-Dist: flake8-debugger>=3.2.1; extra == "dev"
Requires-Dist: pytest>=5.4.3; extra == "dev"
Requires-Dist: pytest-cov>=2.9.0; extra == "dev"
Requires-Dist: pytest-raises>=0.11; extra == "dev"
Requires-Dist: bump2version>=1.0.1; extra == "dev"
Requires-Dist: coverage>=5.1; extra == "dev"
Requires-Dist: ipython>=7.15.0; extra == "dev"
Requires-Dist: m2r2>=0.2.7; extra == "dev"
Requires-Dist: Sphinx>=3.4.3; extra == "dev"
Requires-Dist: sphinx_rtd_theme>=0.5.1; extra == "dev"
Requires-Dist: tox>=3.15.2; extra == "dev"
Requires-Dist: twine>=3.1.1; extra == "dev"
Requires-Dist: wheel>=0.34.2; extra == "dev"
Provides-Extra: all
Requires-Dist: vessel_analysis_3d[dev]; extra == "all"
Requires-Dist: vessel_analysis_3d[test]; extra == "all"
Requires-Dist: vessel_analysis_3d[setup]; extra == "all"
Dynamic: license-file
